views/__init__.py
views/py.typed
views/utilities.py
views/views.py
views/tests/__init__.py
views/tests/test_utilities.py
views_py-2.0.0.dist-info/LICENSE
views_py-2.0.0.dist-info/METADATA
views_py-2.0.0.dist-info/WHEEL
views_py-2.0.0.dist-info/top_level.txt
views_py-2.0.0.dist-info/RECORD
