Metadata-Version: 2.1
Name: views-py
Version: 2.0.0
Summary: Views and related utilities for generic sequence types.
Author: Braedyn L
License: MIT License
Project-URL: Homepage, https://github.com/braedynl/views-py
Project-URL: Source, https://github.com/braedynl/views-py
Project-URL: Bug Tracker, https://github.com/braedynl/views-py/issues
Keywords: view,views,windowing,sequences,sequence-viewer
Classifier: Programming Language :: Python :: 3
Classifier: Programming Language :: Python :: 3.9
Classifier: Programming Language :: Python :: 3.10
Classifier: Programming Language :: Python :: 3.11
Classifier: License :: OSI Approved :: MIT License
Classifier: Operating System :: OS Independent
Classifier: Topic :: Software Development :: Libraries :: Python Modules
Requires-Python: >=3.9
License-File: LICENSE
